{

    "RESPONSE_STATUS_MESSAGE_INTERNAL_SERVER_ERROR" :	"¡Error Interno del Servidor!" ,
    "RESPONSE_STATUS_MESSAGE_NOT_FOUND" :	"¡Resiste no encontrado!" ,
    "RESPONSE_STATUS_MESSAGE_AUTHORIZATION_ERROR" :	"¡El usuario no está permitido!" ,
    "LOGIN_SUCCESSFUL" :	"Conexión exitosa",
    "LOGIN_FAILED" :	"Error de inicio de sesion.",
    "LOGOUT_SUCCESSFUL" :	"Conexión exitosa",
    "LOGOUT_FAILED" :	"La desconexión ha fallado",
    "USER_NOT_FOUND" :	"El usuario no existe lo siento",
    "LOGIN_UN_SUCCESSFUL_WITHOUT_PASSWORD" :	"Defina su contraseña antes de conectarse",
    "INVALID_EMAIL" :	"Email inválido",
    "INVALID_PASSWORD" :	"Contraseña incorrecta.",
    "URL_CORRECT" :	"Su enlace para restablecer la contraseña es válido",
    "URL_EXPIRED" :	"Su enlace para restablecer la contraseña ha expirado",
    "LINK_INCORRECT" :	"Su enlace para restablecer la contraseña es incorrecto",
    "INVITE_URL_CORRECT" :	"Su enlace para definir la contraseña es válido",
    "INVITE_URL_EXPIRED" :	"Su código de invitación ha expirado",
    "INVITE_LINK_INCORRECT" :	"Su código de invitación es incorrecto",
    "EMAIL_SENT" :	"Verifique su casilla de mensajería El enlace se compartió para modificar la contraseña",
    "PASSWORD_RESET_SUCCESSFULLY" :	"Restablecer la contraseña exitosa",
    "PASSWORD_RESET_UN_SUCCESSFULLY" :	"No se puede restablecer la contraseña",
    "CURRENT_PASSWORD_INVALID" :	"La contraseña actual no es válida",
    "INITIAL_PASSWORD_SETUP_SUCCESS" :	"Configuración de la contraseña exitosa",
    "INITIAL_PASSWORD_SETUP_ERROR" :	"Configuración de la contraseña no succrcès",
    "PASSWORD_CHANGE_SUCCESSFULLY" :	"Cambio de contraseña exitoso.",
    "PASSWORD_CHANGE_UN_SUCCESSFULLY" :	"Imposible actualizar una nueva contraseña",
    "PASSWORD_MISMATCH" :	"Nueva contraseña y confirmar que la contraseña no se corresponde",
    "EMAIL_ERROR_MISSING" :	"Falta el correo electrónico",
    "EMAIL_ERROR_EMPTY" :	"El correo electrónico está vacío",
    "EMAIL_ERROR_INVALID" :	"Dirección de correo electrónico no válida",
    "EMAIL_UNIQUE" :	"El correo electrónico debe ser único",
    "NAME_MISSING" :	"Falta el nombre",
    "NAME_EMPTY" :	"El nombre está vacío",
    "PASSWORD_ERROR_MISSING" :	"Falta la contraseña",
    "PASSWORD_ERROR_EMPTY" :	"La contraseña está vacía",
    "PASSWORD_LENGTH" :	"Contraseña Ingrese Min 6 Longitud",
    "IN_VALID_PASSWORD_TYPE" :	"La contraseña debe contener 1 cifra, 1 capital, 1 especial debe estar entre 6 y 15 caracteres",
    "OLD_PASSWORD_REQUIRED" :	"Ingrese la contraseña anterior",
    "NEW_PASSWORD_REQUIRED" :	"Ingrese la contraseña de 4 dígitos",
    "CONFIRM_PASSWORD" :	"Confirme que se requiere el campo de contraseña",
    "IN_VALID_CONFIRM_PASSWORD" :	"Confirmar que la contraseña no corresponde a la contraseña",
    "TOKEN_INVALID" :	"Tu token no es válido",
    "TOKEN_REQUIRED" :	"Ingrese el token válido",
    "ADMIN_AND_BRAND_ACCESS" :	"Solo el administrador y la marca pueden acceder a él",
    "USERS_FOUND" :	"Los usuarios han encontrado",
    "USERS_NOT_FOUND" :	"Usuario no encontrado." ,
    "USERS_ADDED" :	"Los usuarios han grabado" ,
    "USERS_NOT_ADDED" :	"Usuarios no registrados" ,
    "USERS_ADD_REJECTED" :	"Los correos electrónicos de los usuarios deben ser únicos",
    "USER_UPDATED" :	"Actualización del usuario correctamente" ,
    "USER_NOT_UPDATE" :	"Usuario no actualizado",
    "USER_DELETED" :	"El usuario elimina con éxito" ,
    "USER_NOT_DELETE" :	"El usuario no se elimina" ,
    "FIRST_NAME_REQUIRED" :	"Nombre (obligatorio)",
    "FIRST_NAME_ALREADY_EXISTS" :	"La cuenta fue creada con un nombre dado",
    "LAST_NAME_REQUIRED" :	"Nombre de la familia requerido",
    "LAST_NAME_ALREADY_EXISTS" :	"La cuenta fue creada con un apellido dado",
    "EMAIL_EXISTS" :	"El usuario con el mismo correo electrónico ya existe" ,
    "EMAIL_REQUIRED" :	"Correo electronico (requerido)",
    "EMAIL_NOT_EMPTY" :	"Correo electrónico no vacío",
    "EMAIL_INVALID" :	"Email inválido",
    "EMAIL_ALREADY_EXISTS" :	"La cuenta ya existe con el correo dado",
    "PASSWORD_REQUIRED" :	"Se requiere contraseña" ,
    "PHONE_NUMBER_REQUIRED" :	"Ingrese el número de teléfono",
    "CATEGORY_ADDED" :	"Categoría agregar con éxito",
    "CATEGORY_NOT_ADDED" :	"Categoría no agregada",
    "CATEGORY_NOT_IN_REQ_FILE" :	"Categoría no agregar req cola",
    "CATEGORY_UPDATED" :	"Categoría de actualización exitosa",
    "CATEGORY_NOT_UPDATED" :	"Categoría no actualizada",
    "CATEGORY_DELETED" :	"Categoría eliminada con éxito",
    "CATEGORY_NOT_DELETED" :	"Categoría no eliminada",
    "CATEGORY_TYPE_REQUIRED" :	"Ingrese el tipo de categoría",
    "CATEGORY_IMAGE_REQUIRED" :	"Agregue la imagen de categoría",
    "CATEGORY_FOUND" :	"Categoría encontrada",
    "CATEGORY_NOT_FOUND" :	"Categoría no deseada",
    "SUB_CATEGORY_ADDED" :	"La subcategoría agrega con éxito",
    "SUB_CATEGORY_NOT_ADDED" :	"Subcategoría no dudosa",
    "SUB_CATEGORY_UPDATED" :	"Subcategoría actualizada con éxito",
    "SUB_CATEGORY_NOT_UPDATED" :	"Subcategoría no actualizada",
    "SUB_CATEGORY_DELETED" :	"Subcategoría eliminada con éxito",
    "SUB_CATEGORY_NOT_DELETED" :	"Subcategoría de nocturna",
    "SUB_CATEGORY_NAME_REQUIRED" :	"Ingrese el nombre de la subcategoría",
    "CATEGORIES_ID_REQUIRED" :	"Ingrese las categorías de identificación",
    "SUB_CATEGORY_FOUND" :	"Consejo de categoría encontrada",
    "SUB_CATEGORY_NOT_FOUND" :	"Consejo de categoría no encontrada",
    "PRODUCT_ADDED" :	"El producto agrega con éxito",
    "PRODUCT_NOT_ADDED" :	"Producto no agregado",
    "PRODUCT_UPDATED" :	"Producto actualizado con éxito",
    "PRODUCT_NOT_UPDATED" :	"Producto no actualizado",
    "PRODUCT_DELETED" :	"Producto eliminado con éxito",
    "PRODUCT_NOT_DELETED" :	"Producto no eliminado",
    "PRODUCT_NAME_REQUIRED" :	"Ingrese el nombre del producto",
    "PRODUCT_PRICE_REQUIRED" :	"Ingrese el precio del producto",
    "PRODUCT_DESCRIPTION_REQUIRED" :	"Ingrese la descripción del producto",
    "SUB_CATEGORIES_ID_REQUIRED" :	"Ingrese el sub_categorías_id",
    "PRODUCT_FOUND" :	"Producto encontrado",
    "PRODUCT_NOT_FOUND" :	"Producto no encontrado",
    "CATEGORIES_ID_NOT_MATCH": "La identificación de las categorías no coincide, ingrese una identificación válida",
    "SUB_CATEGORIES_ID_NOT_MATCH": "La identificación de las subcategorías no coincide, ingrese una identificación válida",
    "CATEGORY_DISABLE": "Categoría deshabilitada con éxito",
    "CATEGORY_NOT_DISABLE": "Categoría no deshabilitada",
    "SUB_CATEGORY_DISABLE": "Subcategoría deshabilitada con éxito",
    "SUB_CATEGORY_NOT_DISABLE": "Subcategoría no deshabilitada",
    "PRODUCT_DISABLE": "Producto deshabilitado con éxito",
    "PRODUCT_NOT_DISABLE": "Producto no deshabilitado",
    "CUSTOMER_UPDATED" : "Actualización del cliente correctamente.",
    "CUSTOMER_NOT_UPDATE" : "Cliente no actualizado",
    "CUSTOMER_DELETED" : "Eliminar el cliente con éxito",
    "CUSTOMER_NOT_DELETE" : "Cliente no eliminado",
    "CUSTOMER_DISABLE":"El cliente deshabilita con éxito",
    "CUSTOMER_NOT_DISABLE" : "El cliente no deshabilita",
    "CUSTOMER_FOUND":"Cliente encontrado",
    "CUSTOMER_NOT_FOUND" : "Cliente no encontrado.",
    "NOT_A_CUSTOMER": "Tu papel no es una cliente",
    "BRAND_UPDATED": "Actualización de marca con éxito.",
    "BRAND_NOT_UPDATE": "Marca no actualizada",
    "BRAND_DELETED": "Marca eliminar con éxito",
    "BRAND_NOT_DELETE": "Marca no eliminada",
    "BRAND_DISABLE": "La marca deshabilitar con éxito",
    "BRAND_NOT_DISABLE": "La marca no se deshabilita",
    "BRAND_FOUND": "Marca encontrada",
    "BRAND_NOT_FOUND": "Marca no encontrada.",
    "NOT_A_BRAND": "Tu papel no es una marca",
    "INFLUENCER_UPDATED": "Actualización del influencer con éxito.",
    "INFLUENCER_NOT_UPDATE": "Influencer no actualizado",
    "INFLUENCER_DELETED": "Influencer Eliminar con éxito",
    "INFLUENCER_NOT_DELETE": "Influencer no eliminado",
    "INFLUENCER_DISABLE": "El influencer se desactiva con éxito",
    "INFLUENCER_NOT_DISABLE": "Influencer no deshabilitar",
    "INFLUENCER_FOUND": "Influencer encontrado",
    "INFLUENCER_NOT_FOUND": "Influencer no encontrado.",
    "NOT_A_INFLUENCER": "Tu papel no es un influencer"

        
}